pytest_attributes/__init__.py
pytest_attributes/attributes.py
pytest_attributes-1.0.0.dist-info/LICENSE
pytest_attributes-1.0.0.dist-info/METADATA
pytest_attributes-1.0.0.dist-info/WHEEL
pytest_attributes-1.0.0.dist-info/entry_points.txt
pytest_attributes-1.0.0.dist-info/top_level.txt
pytest_attributes-1.0.0.dist-info/RECORD
