Metadata-Version: 2.1
Name: pytest-attributes
Version: 1.0.0
Summary: A plugin that allows users to add attributes to their tests. These attributes can then be referenced by fixtures or the test itself.
Author-email: Babak Michael Engheta <michaelengheta55@gmail.com>
Maintainer-email: Babak Michael Engheta <michaelengheta55@gmail.com>
License: 
Project-URL: Repository, https://github.com/MichaelE55/pytest-attributes
Classifier: Framework :: Pytest
Classifier: Development Status :: 4 - Beta
Classifier: Intended Audience :: Developers
Classifier: Topic :: Software Development :: Testing
Classifier: Operating System :: OS Independent
Classifier: Programming Language :: Python
Classifier: Programming Language :: Python :: 3.8
Classifier: Programming Language :: Python :: 3.9
Classifier: Programming Language :: Python :: 3.10
Classifier: Programming Language :: Python :: 3.11
Classifier: Programming Language :: Python :: 3.12
Classifier: Programming Language :: Python :: 3 :: Only
Classifier: Programming Language :: Python :: Implementation :: CPython
Classifier: Programming Language :: Python :: Implementation :: PyPy
Classifier: License :: OSI Approved :: BSD License
Requires-Python: >=3.8
License-File: LICENSE
Requires-Dist: pytest >=6.2.0
